theeverythinglibrary/__init__.py
theeverythinglibrary/encoding.py
theeverythinglibrary/encryption.py
theeverythinglibrary/enviroment.py
theeverythinglibrary/exceptions.py
theeverythinglibrary/files.py
theeverythinglibrary/hashing.py
theeverythinglibrary/math.py
theeverythinglibrary/password.py
theeverythinglibrary/regex.py
theeverythinglibrary/sorting.py
theeverythinglibrary/translator.py
theeverythinglibrary/utilities.py
theeverythinglibrary/web.py
theeverythinglibrary-0.3.12.dist-info/LICENSE
theeverythinglibrary-0.3.12.dist-info/METADATA
theeverythinglibrary-0.3.12.dist-info/WHEEL
theeverythinglibrary-0.3.12.dist-info/top_level.txt
theeverythinglibrary-0.3.12.dist-info/RECORD
