Metadata-Version: 2.1
Name: theeverythinglibrary
Version: 0.3.12
Summary: Library with a module for almost everything
Home-page: https://github.com/RobertArnosson/TheEverythingLibrary
Author: Robert Arnorsson
Project-URL: Documentation, https://github.com/RobertArnosson/TheEverythingLibrary/wiki
Project-URL: Bug Reports, https://github.com/RobertArnosson/TheEverythingLibrary/issues
Project-URL: Source, https://github.com/RobertArnosson/TheEverythingLibrary
Classifier: Development Status :: 4 - Beta
Classifier: Intended Audience :: Developers
Classifier: Intended Audience :: Science/Research
Classifier: Topic :: Security :: Cryptography
Classifier: Topic :: Software Development :: Build Tools
Classifier: License :: OSI Approved :: MIT License
Classifier: Programming Language :: Python :: 3.9
Classifier: Programming Language :: Python :: 3.10
Classifier: Programming Language :: Python :: 3.11
Classifier: Programming Language :: Python :: 3 :: Only
Requires-Python: >=3.9
License-File: LICENSE
Requires-Dist: cryptography
Requires-Dist: argon2-cffi
Requires-Dist: uuid
Requires-Dist: requests
Requires-Dist: googletrans
